cel/__init__.py
cel/__main__.py
cel/cel.cp311-win_amd64.pyd
cel/cel.pyi
cel/cli.py
cel/py.typed
cel/stdlib.py
common_expression_language-0.5.3.dist-info/METADATA
common_expression_language-0.5.3.dist-info/WHEEL
common_expression_language-0.5.3.dist-info/entry_points.txt
common_expression_language-0.5.3.dist-info/licenses/LICENSE
common_expression_language-0.5.3.dist-info/RECORD
