Metadata-Version: 2.4
Name: common-expression-language
Version: 0.5.3
Classifier: Programming Language :: Rust
Classifier: Programming Language :: Python :: Implementation :: CPython
Classifier: Programming Language :: Python :: Implementation :: PyPy
Requires-Dist: typer>=0.12.0
Requires-Dist: rich>=13.0.0
Requires-Dist: prompt-toolkit>=3.0.0
Requires-Dist: pygments>=2.0.0
License-File: LICENSE
Summary: Python bindings for the Common Expression Language (CEL)
Author-email: Brian Thorne <brian@hardbyte.nz>
Requires-Python: >=3.11
Project-URL: Homepage, https://github.com/hardbyte/python-common-expression-language
Project-URL: Repository, https://github.com/hardbyte/python-common-expression-language
